[
  {"id":"w2507","en":"wake up","ua":"прокидатися","pos":"phrasal","level":"A2","topic":"daily life","freqRank":2507,"example":{"en":"She wakes up early to prepare breakfast.","ua":"Вона прокидається рано, щоб приготувати сніданок."}},
  {"id":"w2508","en":"sit down","ua":"сідати","pos":"phrasal","level":"A2","topic":"daily life","freqRank":2508,"example":{"en":"Please sit down and make yourself comfortable.","ua":"Будь ласка, сядьте і почувайтеся як вдома."}},
  {"id":"w2509","en":"stand up","ua":"вставати","pos":"phrasal","level":"A2","topic":"daily life","freqRank":2509,"example":{"en":"Everyone should stand up when the teacher enters.","ua":"Всі повинні вставати, коли вчитель заходить."}},
  {"id":"w2510","en":"come in","ua":"заходити","pos":"phrasal","level":"A2","topic":"daily life","freqRank":2510,"example":{"en":"Come in, the door is open for you.","ua":"Заходьте, двері відчинені для вас."}},
  {"id":"w2511","en":"go out","ua":"виходити (з дому)","pos":"phrasal","level":"A2","topic":"daily life","freqRank":2511,"example":{"en":"We go out for dinner every Friday evening.","ua":"Ми виходимо вечеряти кожної п'ятниці."}},
  {"id":"w2512","en":"put on","ua":"одягати","pos":"phrasal","level":"A2","topic":"clothing","freqRank":2512,"example":{"en":"Put on your coat before going outside.","ua":"Одягни пальто, перш ніж виходити."}},
  {"id":"w2513","en":"take off","ua":"знімати (одяг)","pos":"phrasal","level":"A2","topic":"clothing","freqRank":2513,"example":{"en":"Take off your shoes at the front door.","ua":"Зніміть взуття біля вхідних дверей."}},
  {"id":"w2514","en":"pick up","ua":"піднімати, підбирати","pos":"phrasal","level":"A2","topic":"daily life","freqRank":2514,"example":{"en":"Can you pick up the books from the floor?","ua":"Ти можеш підняти книги з підлоги?"}},
  {"id":"w2515","en":"put down","ua":"класти, ставити","pos":"phrasal","level":"A2","topic":"daily life","freqRank":2515,"example":{"en":"Put down your phone and listen to me.","ua":"Відклади телефон і слухай мене."}},
  {"id":"w2516","en":"turn on","ua":"вмикати","pos":"phrasal","level":"A2","topic":"home","freqRank":2516,"example":{"en":"Turn on the light, it is too dark here.","ua":"Увімкни світло, тут надто темно."}},
  {"id":"w2517","en":"turn off","ua":"вимикати","pos":"phrasal","level":"A2","topic":"home","freqRank":2517,"example":{"en":"Turn off the television before you go to bed.","ua":"Вимкни телевізор перед тим, як іти спати."}},
  {"id":"w2518","en":"put away","ua":"прибирати, класти на місце","pos":"phrasal","level":"A2","topic":"home","freqRank":2518,"example":{"en":"Please put away your toys before dinner tonight.","ua":"Будь ласка, прибери іграшки до вечері сьогодні."}},
  {"id":"w2519","en":"look for","ua":"шукати","pos":"phrasal","level":"A2","topic":"daily life","freqRank":2519,"example":{"en":"I am looking for my keys all morning.","ua":"Я шукаю свої ключі весь ранок."}},
  {"id":"w2520","en":"go back","ua":"повертатися","pos":"phrasal","level":"A2","topic":"travel","freqRank":2520,"example":{"en":"We need to go back home before it rains.","ua":"Нам потрібно повернутися додому, поки не пішов дощ."}},
  {"id":"w2521","en":"come back","ua":"повертатися назад","pos":"phrasal","level":"A2","topic":"travel","freqRank":2521,"example":{"en":"My brother will come back from London next week.","ua":"Мій брат повернеться з Лондона наступного тижня."}},
  {"id":"w2522","en":"give up","ua":"здаватися, припиняти спроби","pos":"phrasal","level":"A2","topic":"emotions","freqRank":2522,"example":{"en":"Do not give up when things get difficult.","ua":"Не здавайся, коли стає важко."}},
  {"id":"w2523","en":"look up","ua":"шукати (слово в словнику)","pos":"phrasal","level":"A2","topic":"school","freqRank":2523,"example":{"en":"Look up this word in your dictionary.","ua":"Пошукай це слово у своєму словнику."}},
  {"id":"w2524","en":"write down","ua":"записувати","pos":"phrasal","level":"A2","topic":"school","freqRank":2524,"example":{"en":"Write down the homework before the lesson ends.","ua":"Запиши домашнє завдання до кінця уроку."}},
  {"id":"w2525","en":"hang up","ua":"класти слухавку","pos":"phrasal","level":"A2","topic":"communication","freqRank":2525,"example":{"en":"She said goodbye and then hung up the phone.","ua":"Вона попрощалася, а потім поклала слухавку."}},
  {"id":"w2526","en":"call back","ua":"передзвонювати","pos":"phrasal","level":"A2","topic":"communication","freqRank":2526,"example":{"en":"I missed your call, I will call back later.","ua":"Я пропустив твій дзвінок, передзвоню пізніше."}},
  {"id":"w2527","en":"try on","ua":"приміряти (одяг)","pos":"phrasal","level":"A2","topic":"shopping","freqRank":2527,"example":{"en":"Can I try on this jacket in a smaller size?","ua":"Можна приміряти цей піджак меншого розміру?"}},
  {"id":"w2528","en":"get in","ua":"сідати в транспортний засіб","pos":"phrasal","level":"A2","topic":"transport","freqRank":2528,"example":{"en":"Get in the car, we are already late.","ua":"Сідай у машину, ми вже спізнюємося."}},
  {"id":"w2529","en":"get out","ua":"виходити з транспортного засобу","pos":"phrasal","level":"A2","topic":"transport","freqRank":2529,"example":{"en":"Get out of the taxi at the main square.","ua":"Вийди з таксі на головній площі."}},
  {"id":"w2530","en":"run out","ua":"закінчуватися (про запас)","pos":"phrasal","level":"A2","topic":"daily life","freqRank":2530,"example":{"en":"We have run out of milk again.","ua":"У нас знову скінчилося молоко."}},
  {"id":"w2531","en":"find out","ua":"дізнаватися","pos":"phrasal","level":"A2","topic":"general","freqRank":2531,"example":{"en":"I need to find out what time the shop opens.","ua":"Мені потрібно дізнатися, о котрій відчиняється магазин."}},
  {"id":"w2532","en":"come on","ua":"давай, поспішай (спонукання)","pos":"phrasal","level":"A2","topic":"general","freqRank":2532,"example":{"en":"Come on, we will miss the bus to school.","ua":"Давай, ми спізнимось на шкільний автобус."}},
  {"id":"w2533","en":"go on","ua":"тривати, продовжуватися","pos":"phrasal","level":"A2","topic":"general","freqRank":2533,"example":{"en":"The concert went on for more than three hours.","ua":"Концерт тривав понад три години."}},
  {"id":"w2534","en":"look after","ua":"доглядати, піклуватися","pos":"phrasal","level":"A2","topic":"family","freqRank":2534,"example":{"en":"My grandmother looks after the children while we work.","ua":"Моя бабуся доглядає дітей, поки ми працюємо."}},
  {"id":"w2535","en":"bring up","ua":"виховувати (дитину)","pos":"phrasal","level":"A2","topic":"family","freqRank":2535,"example":{"en":"Her parents brought her up in a small village.","ua":"Її батьки виховали її в маленькому селі."}},
  {"id":"w2536","en":"take out","ua":"виносити (сміття); діставати","pos":"phrasal","level":"A2","topic":"home","freqRank":2536,"example":{"en":"Please take out the rubbish before you sleep.","ua":"Будь ласка, винеси сміття перед сном."}},
  {"id":"w2537","en":"throw away","ua":"викидати","pos":"phrasal","level":"A2","topic":"home","freqRank":2537,"example":{"en":"Throw away the old newspapers in the recycling bin.","ua":"Викинь старі газети в контейнер для переробки."}},
  {"id":"w2538","en":"come over","ua":"заходити в гості","pos":"phrasal","level":"A2","topic":"daily life","freqRank":2538,"example":{"en":"Can you come over for dinner on Saturday night?","ua":"Ти можеш зайти на вечерю в суботу ввечері?"}},
  {"id":"w2539","en":"clean up","ua":"прибирати, наводити лад","pos":"phrasal","level":"A2","topic":"home","freqRank":2539,"example":{"en":"We need to clean up the kitchen after cooking.","ua":"Нам потрібно прибрати кухню після готування."}},
  {"id":"w2540","en":"wash up","ua":"мити посуд","pos":"phrasal","level":"A2","topic":"home","freqRank":2540,"example":{"en":"Could you wash up while I dry the dishes?","ua":"Ти міг би помити посуд, поки я витираю?"}},
  {"id":"w2541","en":"grow up","ua":"рости, дорослішати","pos":"phrasal","level":"A2","topic":"family","freqRank":2541,"example":{"en":"I grew up in a small town near the sea.","ua":"Я виріс у невеликому місті біля моря."}},
  {"id":"w2542","en":"eat up","ua":"з'їдати все до кінця","pos":"phrasal","level":"A2","topic":"food","freqRank":2542,"example":{"en":"Eat up your vegetables and you can have dessert.","ua":"З'їж всі овочі, і тоді зможеш отримати десерт."}},
  {"id":"w2543","en":"drink up","ua":"випивати все до кінця","pos":"phrasal","level":"A2","topic":"food","freqRank":2543,"example":{"en":"Drink up your juice before it gets warm.","ua":"Допий сік, поки він не нагрівся."}},
  {"id":"w2544","en":"pay back","ua":"повертати позичені гроші","pos":"phrasal","level":"A2","topic":"money","freqRank":2544,"example":{"en":"I will pay you back as soon as I can.","ua":"Я поверну тобі гроші, щойно зможу."}},
  {"id":"w2545","en":"ask for","ua":"просити (щось)","pos":"phrasal","level":"A2","topic":"communication","freqRank":2545,"example":{"en":"He asked for help with the difficult math problem.","ua":"Він попросив допомоги зі складною задачею з математики."}},
  {"id":"w2546","en":"wait for","ua":"чекати на когось або щось","pos":"phrasal","level":"A2","topic":"daily life","freqRank":2546,"example":{"en":"I have been waiting for the bus for twenty minutes.","ua":"Я чекаю на автобус уже двадцять хвилин."}},
  {"id":"w2547","en":"care for","ua":"піклуватися про хворого","pos":"phrasal","level":"A2","topic":"health","freqRank":2547,"example":{"en":"She cares for her elderly father every single day.","ua":"Вона щодня піклується про свого літнього батька."}},
  {"id":"w2548","en":"cut down","ua":"скорочувати (кількість)","pos":"phrasal","level":"A2","topic":"health","freqRank":2548,"example":{"en":"We must cut down our energy use at home.","ua":"Ми повинні скоротити споживання енергії вдома."}},
  {"id":"w2549","en":"fill in","ua":"заповнювати (бланк або форму)","pos":"phrasal","level":"A2","topic":"work","freqRank":2549,"example":{"en":"Please fill in this form with your personal details.","ua":"Будь ласка, заповни цю форму своїми особистими даними."}},
  {"id":"w2550","en":"hand in","ua":"здавати (роботу або завдання)","pos":"phrasal","level":"A2","topic":"school","freqRank":2550,"example":{"en":"Hand in your essays before the end of Friday.","ua":"Здайте есе до кінця п'ятниці."}},
  {"id":"w2551","en":"open up","ua":"відкриватися, розкриватися","pos":"phrasal","level":"A2","topic":"emotions","freqRank":2551,"example":{"en":"It took years for him to open up about his past.","ua":"Йому знадобилися роки, щоб відкритися про своє минуле."}},
  {"id":"w2552","en":"slow down","ua":"уповільнюватися","pos":"phrasal","level":"A2","topic":"transport","freqRank":2552,"example":{"en":"Slow down, there is a school ahead on the road.","ua":"Знизь швидкість, попереду на дорозі школа."}},
  {"id":"w2553","en":"speed up","ua":"прискорюватися","pos":"phrasal","level":"A2","topic":"transport","freqRank":2553,"example":{"en":"The train began to speed up after leaving the station.","ua":"Поїзд почав прискорюватися, залишивши станцію."}},
  {"id":"w2554","en":"turn up","ua":"з'являтися (несподівано)","pos":"phrasal","level":"A2","topic":"general","freqRank":2554,"example":{"en":"He turned up at the party without an invitation.","ua":"Він з'явився на вечірці без запрошення."}},
  {"id":"w2555","en":"turn down","ua":"відмовляти, відхиляти пропозицію","pos":"phrasal","level":"A2","topic":"general","freqRank":2555,"example":{"en":"She turned down the job offer for personal reasons.","ua":"Вона відхилила пропозицію роботи з особистих причин."}},
  {"id":"w2556","en":"go ahead","ua":"продовжувати, починати (дозвіл)","pos":"phrasal","level":"A2","topic":"general","freqRank":2556,"example":{"en":"Go ahead and start the meeting without us.","ua":"Продовжуйте та починайте нараду без нас."}},
  {"id":"w2557","en":"set off","ua":"вирушати в подорож","pos":"phrasal","level":"A2","topic":"travel","freqRank":2557,"example":{"en":"We set off early to avoid the morning traffic.","ua":"Ми вирушили рано, щоб уникнути ранкових заторів."}},
  {"id":"w2558","en":"drop off","ua":"підвозити до певного місця","pos":"phrasal","level":"A2","topic":"transport","freqRank":2558,"example":{"en":"Can you drop me off near the train station?","ua":"Ти можеш підвезти мене до залізничної станції?"}},
  {"id":"w2559","en":"pick out","ua":"вибирати зі списку або групи","pos":"phrasal","level":"A2","topic":"shopping","freqRank":2559,"example":{"en":"She picked out a blue dress for the party.","ua":"Вона вибрала синю сукню для вечірки."}},
  {"id":"w2560","en":"take back","ua":"брати свої слова назад","pos":"phrasal","level":"A2","topic":"communication","freqRank":2560,"example":{"en":"He took back everything he said during the argument.","ua":"Він узяв назад усе, що сказав під час суперечки."}},
  {"id":"w2561","en":"put back","ua":"класти назад на місце","pos":"phrasal","level":"A2","topic":"daily life","freqRank":2561,"example":{"en":"Please put back the book when you are done.","ua":"Будь ласка, поклади книгу назад, коли закінчиш."}},
  {"id":"w2562","en":"bring back","ua":"повертати (предмет)","pos":"phrasal","level":"A2","topic":"general","freqRank":2562,"example":{"en":"Bring back my umbrella when you see me tomorrow.","ua":"Поверни мою парасолю, коли побачиш мене завтра."}},
  {"id":"w2563","en":"keep on","ua":"продовжувати (попри труднощі)","pos":"phrasal","level":"A2","topic":"general","freqRank":2563,"example":{"en":"Keep on practising and you will improve quickly.","ua":"Продовжуй практикуватись, і ти швидко покращишся."}},
  {"id":"w2564","en":"go away","ua":"їхати у відпустку або поїздку","pos":"phrasal","level":"A2","topic":"travel","freqRank":2564,"example":{"en":"We are going away to the mountains this weekend.","ua":"Ми їдемо в гори цього вихідного."}},
  {"id":"w2565","en":"come along","ua":"приєднуватися, супроводжувати","pos":"phrasal","level":"A2","topic":"general","freqRank":2565,"example":{"en":"You are welcome to come along to the concert tonight.","ua":"Ти можеш приєднатися до нас на концерт сьогодні."}},
  {"id":"w2566","en":"take away","ua":"забирати (їжу) з собою","pos":"phrasal","level":"A2","topic":"food","freqRank":2566,"example":{"en":"I will take away a pizza for dinner tonight.","ua":"Я візьму піцу з собою на вечерю сьогодні."}},
  {"id":"w2567","en":"set up","ua":"організовувати, засновувати","pos":"phrasal","level":"B1","topic":"business","freqRank":2567,"example":{"en":"They set up a new company last spring.","ua":"Минулої весни вони заснували нову компанію."}},
  {"id":"w2568","en":"work out","ua":"вирішувати, опрацьовувати деталі","pos":"phrasal","level":"B1","topic":"work","freqRank":2568,"example":{"en":"We need to work out the details of the plan.","ua":"Нам потрібно опрацювати деталі плану."}},
  {"id":"w2569","en":"carry out","ua":"виконувати (завдання або план)","pos":"phrasal","level":"B1","topic":"work","freqRank":2569,"example":{"en":"The team carried out the experiment successfully last month.","ua":"Минулого місяця команда успішно провела експеримент."}},
  {"id":"w2570","en":"point out","ua":"вказувати на (помилку або факт)","pos":"phrasal","level":"B1","topic":"communication","freqRank":2570,"example":{"en":"She pointed out several mistakes in my report.","ua":"Вона вказала на кілька помилок у моєму звіті."}},
  {"id":"w2571","en":"figure out","ua":"з'ясовувати, розуміти","pos":"phrasal","level":"B1","topic":"general","freqRank":2571,"example":{"en":"I cannot figure out how this machine works.","ua":"Я не можу розібратися, як працює ця машина."}},
  {"id":"w2572","en":"deal with","ua":"вирішувати, мати справу з","pos":"phrasal","level":"B1","topic":"work","freqRank":2572,"example":{"en":"He deals with customer complaints every working day.","ua":"Він вирішує скарги клієнтів кожного робочого дня."}},
  {"id":"w2573","en":"put off","ua":"відкладати на пізніше","pos":"phrasal","level":"B1","topic":"general","freqRank":2573,"example":{"en":"Do not put off important tasks until tomorrow.","ua":"Не відкладай важливі справи на завтра."}},
  {"id":"w2574","en":"take up","ua":"починати займатися (хобі)","pos":"phrasal","level":"B1","topic":"hobby","freqRank":2574,"example":{"en":"She took up painting after she retired from work.","ua":"Вона захопилася малюванням після виходу на пенсію."}},
  {"id":"w2575","en":"break down","ua":"ламатися, виходити з ладу","pos":"phrasal","level":"B1","topic":"technology","freqRank":2575,"example":{"en":"My laptop broke down during the important presentation.","ua":"Мій ноутбук зламався під час важливої презентації."}},
  {"id":"w2576","en":"make up","ua":"вигадувати (неправду)","pos":"phrasal","level":"B1","topic":"communication","freqRank":2576,"example":{"en":"He made up an excuse to leave the party early.","ua":"Він вигадав відмовку, щоб піти з вечірки раніше."}},
  {"id":"w2577","en":"come up with","ua":"придумувати (ідею або рішення)","pos":"phrasal","level":"B1","topic":"general","freqRank":2577,"example":{"en":"Can you come up with a better solution to this?","ua":"Чи можеш ти придумати краще рішення для цього?"}},
  {"id":"w2578","en":"get along","ua":"ладити, мати добрі стосунки","pos":"phrasal","level":"B1","topic":"general","freqRank":2578,"example":{"en":"The two colleagues get along very well at work.","ua":"Двоє колег дуже добре ладнають на роботі."}},
  {"id":"w2579","en":"give back","ua":"повертати (власність)","pos":"phrasal","level":"B1","topic":"general","freqRank":2579,"example":{"en":"Please give back the money you borrowed from me.","ua":"Будь ласка, поверни гроші, які позичив у мене."}},
  {"id":"w2580","en":"hold on","ua":"зачекати (прохання)","pos":"phrasal","level":"B1","topic":"communication","freqRank":2580,"example":{"en":"Hold on a moment, I need to find the document.","ua":"Зачекай хвилину, мені потрібно знайти документ."}},
  {"id":"w2581","en":"look into","ua":"розслідувати, детально вивчати","pos":"phrasal","level":"B1","topic":"work","freqRank":2581,"example":{"en":"The manager agreed to look into the employee complaint.","ua":"Менеджер погодився розглянути скаргу працівника."}},
  {"id":"w2582","en":"run into","ua":"випадково зустріти","pos":"phrasal","level":"B1","topic":"general","freqRank":2582,"example":{"en":"I ran into my old teacher at the supermarket yesterday.","ua":"Вчора я випадково зустрів свого колишнього вчителя в супермаркеті."}},
  {"id":"w2583","en":"show up","ua":"з'являтися (особисто)","pos":"phrasal","level":"B1","topic":"general","freqRank":2583,"example":{"en":"He always shows up late to every team meeting.","ua":"Він завжди запізнюється на кожну командну нараду."}},
  {"id":"w2584","en":"take on","ua":"наймати на роботу; брати зобов'язання","pos":"phrasal","level":"B1","topic":"work","freqRank":2584,"example":{"en":"The company decided to take on ten new employees.","ua":"Компанія вирішила найняти десятьох нових співробітників."}},
  {"id":"w2585","en":"bring about","ua":"спричиняти (зміни)","pos":"phrasal","level":"B1","topic":"general","freqRank":2585,"example":{"en":"The new law brought about major changes in education.","ua":"Новий закон спричинив суттєві зміни в освіті."}},
  {"id":"w2586","en":"carry on","ua":"продовжувати (попри перешкоди)","pos":"phrasal","level":"B1","topic":"general","freqRank":2586,"example":{"en":"She carried on working despite feeling very unwell.","ua":"Вона продовжувала працювати, незважаючи на погане самопочуття."}},
  {"id":"w2587","en":"fall apart","ua":"розпадатися, руйнуватися","pos":"phrasal","level":"B1","topic":"general","freqRank":2587,"example":{"en":"Their friendship fell apart after the serious argument.","ua":"Їхня дружба розпалася після серйозної сварки."}},
  {"id":"w2588","en":"get over","ua":"оговтуватися (від хвороби або стресу)","pos":"phrasal","level":"B1","topic":"health","freqRank":2588,"example":{"en":"It took me a week to get over that bad cold.","ua":"Мені знадобився тиждень, щоб оговтатися від застуди."}},
  {"id":"w2589","en":"go through","ua":"переживати важкий досвід","pos":"phrasal","level":"B1","topic":"emotions","freqRank":2589,"example":{"en":"She went through a very difficult period last year.","ua":"Минулого року вона пережила дуже важкий період."}},
  {"id":"w2590","en":"keep up","ua":"не відставати, підтримувати темп","pos":"phrasal","level":"B1","topic":"sport","freqRank":2590,"example":{"en":"Run faster, I cannot keep up with your pace.","ua":"Біжи швидше, я не можу встигнути за твоїм темпом."}},
  {"id":"w2591","en":"move on","ua":"рухатися далі (після труднощів)","pos":"phrasal","level":"B1","topic":"general","freqRank":2591,"example":{"en":"It is time to move on and start a new chapter.","ua":"Час рухатися далі і починати нову сторінку."}},
  {"id":"w2592","en":"put up with","ua":"миритися з, терпіти","pos":"phrasal","level":"B1","topic":"general","freqRank":2592,"example":{"en":"I cannot put up with this constant noise any longer.","ua":"Я більше не можу миритися з цим постійним шумом."}},
  {"id":"w2593","en":"sort out","ua":"вирішувати (проблему або непорозуміння)","pos":"phrasal","level":"B1","topic":"general","freqRank":2593,"example":{"en":"We need to sort out this misunderstanding before Monday.","ua":"Нам потрібно вирішити це непорозуміння до понеділка."}},
  {"id":"w2594","en":"bring in","ua":"запроваджувати (правило або систему)","pos":"phrasal","level":"B1","topic":"business","freqRank":2594,"example":{"en":"The company brought in a new safety policy this year.","ua":"Цього року компанія запровадила нову політику безпеки."}},
  {"id":"w2595","en":"catch up","ua":"наздоганяти, надолужувати","pos":"phrasal","level":"B1","topic":"general","freqRank":2595,"example":{"en":"Run faster so you can catch up with them.","ua":"Біжи швидше, щоб наздогнати їх."}},
  {"id":"w2596","en":"cut off","ua":"відключати (зв'язок або постачання)","pos":"phrasal","level":"B1","topic":"general","freqRank":2596,"example":{"en":"The storm cut off the electricity to our village.","ua":"Буря відключила електроенергію в нашому селі."}},
  {"id":"w2597","en":"end up","ua":"опинятися врешті-решт","pos":"phrasal","level":"B1","topic":"general","freqRank":2597,"example":{"en":"We got lost and ended up in the wrong city.","ua":"Ми заблукали і опинилися в чужому місті."}},
  {"id":"w2598","en":"fall behind","ua":"відставати (у навчанні або роботі)","pos":"phrasal","level":"B1","topic":"school","freqRank":2598,"example":{"en":"He fell behind in maths and needed extra lessons.","ua":"Він відстав з математики і потребував додаткових занять."}},
  {"id":"w2599","en":"go off","ua":"спрацьовувати (про будильник)","pos":"phrasal","level":"B1","topic":"home","freqRank":2599,"example":{"en":"My alarm went off at six but I ignored it.","ua":"Мій будильник спрацював о шостій, але я його проігнорував."}},
  {"id":"w2600","en":"hand out","ua":"роздавати (матеріали)","pos":"phrasal","level":"B1","topic":"school","freqRank":2600,"example":{"en":"The teacher handed out worksheets at the start of class.","ua":"Вчитель роздав завдання на початку уроку."}},
  {"id":"w2601","en":"hold back","ua":"стримувати (почуття або людину)","pos":"phrasal","level":"B1","topic":"emotions","freqRank":2601,"example":{"en":"She tried to hold back her tears during the ceremony.","ua":"Вона намагалася стримати сльози під час церемонії."}},
  {"id":"w2602","en":"join in","ua":"приєднуватися до спільної діяльності","pos":"phrasal","level":"B1","topic":"general","freqRank":2602,"example":{"en":"Everyone was singing and I decided to join in too.","ua":"Всі співали, і я вирішив приєднатися теж."}},
  {"id":"w2603","en":"knock out","ua":"перемагати нокаутом","pos":"phrasal","level":"B1","topic":"sport","freqRank":2603,"example":{"en":"The champion knocked out his opponent in round two.","ua":"Чемпіон нокаутував суперника у другому раунді."}},
  {"id":"w2604","en":"lay off","ua":"звільняти (з роботи, скорочення)","pos":"phrasal","level":"B1","topic":"work","freqRank":2604,"example":{"en":"The factory laid off fifty workers due to low demand.","ua":"Фабрика звільнила п'ятдесят робітників через низький попит."}},
  {"id":"w2605","en":"leave out","ua":"пропускати, не включати","pos":"phrasal","level":"B1","topic":"general","freqRank":2605,"example":{"en":"Please do not leave out any important details in the report.","ua":"Будь ласка, не пропускай жодних важливих деталей у звіті."}},
  {"id":"w2606","en":"light up","ua":"освітлюватися, засяяти","pos":"phrasal","level":"B1","topic":"home","freqRank":2606,"example":{"en":"His face lit up when he saw the surprise gift.","ua":"Його обличчя засяяло, коли він побачив несподіваний подарунок."}},
  {"id":"w2607","en":"look forward to","ua":"з нетерпінням чекати на","pos":"phrasal","level":"B1","topic":"emotions","freqRank":2607,"example":{"en":"I look forward to seeing you at the weekend.","ua":"Я з нетерпінням чекаю зустрічі з тобою у вихідні."}},
  {"id":"w2608","en":"pass on","ua":"передавати (інформацію)","pos":"phrasal","level":"B1","topic":"communication","freqRank":2608,"example":{"en":"Please pass on this message to the rest of the team.","ua":"Будь ласка, передай це повідомлення решті команди."}},
  {"id":"w2609","en":"pull out","ua":"виходити (зі справи або угоди)","pos":"phrasal","level":"B1","topic":"business","freqRank":2609,"example":{"en":"The investor pulled out of the project suddenly.","ua":"Інвестор раптово вийшов із проекту."}},
  {"id":"w2610","en":"put forward","ua":"висувати (ідею або пропозицію)","pos":"phrasal","level":"B1","topic":"work","freqRank":2610,"example":{"en":"She put forward an interesting idea at the meeting.","ua":"Вона висунула цікаву ідею на нараді."}},
  {"id":"w2611","en":"rely on","ua":"покладатися на когось або щось","pos":"phrasal","level":"B1","topic":"general","freqRank":2611,"example":{"en":"You can always rely on her to finish on time.","ua":"На неї завжди можна покластися у питанні вчасного завершення."}},
  {"id":"w2612","en":"run over","ua":"збивати на дорозі","pos":"phrasal","level":"B1","topic":"transport","freqRank":2612,"example":{"en":"A car nearly ran over the cat on the street.","ua":"Машина ледь не збила кота на вулиці."}},
  {"id":"w2613","en":"set out","ua":"вирушати в путь","pos":"phrasal","level":"B1","topic":"travel","freqRank":2613,"example":{"en":"They set out on their journey before sunrise this morning.","ua":"Сьогодні вранці вони вирушили в дорогу до сходу сонця."}},
  {"id":"w2614","en":"step up","ua":"підвищувати (зусилля або рівень)","pos":"phrasal","level":"B1","topic":"work","freqRank":2614,"example":{"en":"We need to step up our efforts before the deadline.","ua":"Нам потрібно збільшити зусилля до кінцевого терміну."}},
  {"id":"w2615","en":"take over","ua":"перебирати контроль або керівництво","pos":"phrasal","level":"B1","topic":"business","freqRank":2615,"example":{"en":"A larger company took over the small family business.","ua":"Більша компанія взяла під контроль маленький сімейний бізнес."}},
  {"id":"w2616","en":"turn into","ua":"перетворюватися на щось інше","pos":"phrasal","level":"B1","topic":"general","freqRank":2616,"example":{"en":"The empty building was turned into a cosy café.","ua":"Порожня будівля була перетворена на затишне кафе."}},
  {"id":"w2617","en":"wear out","ua":"зношуватися від використання","pos":"phrasal","level":"B1","topic":"clothing","freqRank":2617,"example":{"en":"These old shoes have completely worn out after two years.","ua":"Це старе взуття повністю зносилося за два роки."}},
  {"id":"w2618","en":"wind down","ua":"розслаблятися після напруженого дня","pos":"phrasal","level":"B1","topic":"emotions","freqRank":2618,"example":{"en":"I usually wind down by reading before going to bed.","ua":"Зазвичай я розслабляюся за читанням перед сном."}},
  {"id":"w2619","en":"break up","ua":"розлучатися з партнером","pos":"phrasal","level":"B1","topic":"family","freqRank":2619,"example":{"en":"They broke up after three years of being together.","ua":"Вони розлучилися після трьох років стосунків."}},
  {"id":"w2620","en":"come across","ua":"натрапляти на (випадково)","pos":"phrasal","level":"B1","topic":"general","freqRank":2620,"example":{"en":"I came across an old photo while cleaning the attic.","ua":"Я натрапив на старе фото, прибираючи горище."}},
  {"id":"w2621","en":"drop out","ua":"кидати навчання або проект","pos":"phrasal","level":"B1","topic":"school","freqRank":2621,"example":{"en":"He dropped out of university to start his own business.","ua":"Він кинув університет, щоб відкрити власний бізнес."}},
  {"id":"w2622","en":"fill out","ua":"заповнювати (анкету або форму)","pos":"phrasal","level":"B1","topic":"work","freqRank":2622,"example":{"en":"You must fill out this application form completely.","ua":"Вам необхідно повністю заповнити цю анкету."}},
  {"id":"w2623","en":"get rid of","ua":"позбуватися (від чогось непотрібного)","pos":"phrasal","level":"B1","topic":"general","freqRank":2623,"example":{"en":"I want to get rid of all this old furniture.","ua":"Я хочу позбутися всіх цих старих меблів."}},
  {"id":"w2624","en":"go over","ua":"повторювати, переглядати","pos":"phrasal","level":"B1","topic":"school","freqRank":2624,"example":{"en":"Let us go over the main points from last week.","ua":"Давайте повторимо основні теми з минулого тижня."}},
  {"id":"w2625","en":"hang out","ua":"проводити час неформально","pos":"phrasal","level":"B1","topic":"daily life","freqRank":2625,"example":{"en":"We often hang out at the park on summer evenings.","ua":"Ми часто проводимо час у парку літніми вечорами."}},
  {"id":"w2626","en":"narrow down","ua":"звужувати (список варіантів)","pos":"phrasal","level":"B1","topic":"general","freqRank":2626,"example":{"en":"We need to narrow down the list to three candidates.","ua":"Нам потрібно скоротити список до трьох кандидатів."}},
  {"id":"w2627","en":"opt out","ua":"відмовлятися від участі","pos":"phrasal","level":"B1","topic":"general","freqRank":2627,"example":{"en":"Employees can opt out of the company pension scheme.","ua":"Працівники можуть відмовитися від пенсійної програми компанії."}},
  {"id":"w2628","en":"pay off","ua":"окупатися, давати результат","pos":"phrasal","level":"B1","topic":"money","freqRank":2628,"example":{"en":"All his hard work finally paid off with a promotion.","ua":"Вся його важка праця нарешті окупилася підвищенням."}},
  {"id":"w2629","en":"save up","ua":"заощаджувати на певну ціль","pos":"phrasal","level":"B1","topic":"money","freqRank":2629,"example":{"en":"She is saving up to buy a new computer.","ua":"Вона заощаджує гроші на новий комп'ютер."}},
  {"id":"w2630","en":"check up on","ua":"перевіряти стан когось або чогось","pos":"phrasal","level":"B1","topic":"general","freqRank":2630,"example":{"en":"The nurse checked up on the patients every two hours.","ua":"Медсестра перевіряла пацієнтів кожні дві години."}},
  {"id":"w2631","en":"make do","ua":"обходитися тим, що є","pos":"phrasal","level":"B1","topic":"general","freqRank":2631,"example":{"en":"We have no butter, so we will make do without it.","ua":"У нас немає масла, тому доведеться обійтися без нього."}},
  {"id":"w2632","en":"tie up","ua":"займати (час або ресурси)","pos":"phrasal","level":"B1","topic":"work","freqRank":2632,"example":{"en":"The project tied up all our resources for three months.","ua":"Проект займав усі наші ресурси протягом трьох місяців."}},
  {"id":"w2633","en":"back up","ua":"робити резервну копію (даних)","pos":"phrasal","level":"B1","topic":"technology","freqRank":2633,"example":{"en":"Always back up your files before updating the system.","ua":"Завжди роби резервні копії файлів перед оновленням системи."}},
  {"id":"w2634","en":"zoom in","ua":"наближати зображення","pos":"phrasal","level":"B1","topic":"technology","freqRank":2634,"example":{"en":"Zoom in on the map to see the street names.","ua":"Наблизь карту, щоб побачити назви вулиць."}},
  {"id":"w2635","en":"log in","ua":"входити в систему (обліковий запис)","pos":"phrasal","level":"B1","topic":"technology","freqRank":2635,"example":{"en":"You need to log in to access your account.","ua":"Вам потрібно увійти, щоб отримати доступ до облікового запису."}},
  {"id":"w2636","en":"sign up","ua":"реєструватися","pos":"phrasal","level":"B1","topic":"general","freqRank":2636,"example":{"en":"Sign up for the newsletter to get the latest updates.","ua":"Підпишіться на розсилку, щоб отримувати останні новини."}},
  {"id":"w2637","en":"account for","ua":"складати (відсоток від цілого)","pos":"phrasal","level":"B2","topic":"business","freqRank":2637,"example":{"en":"Tourism accounts for twenty percent of the country's income.","ua":"Туризм складає двадцять відсотків доходів країни."}},
  {"id":"w2638","en":"back down","ua":"відступати від своєї позиції","pos":"phrasal","level":"B2","topic":"general","freqRank":2638,"example":{"en":"He refused to back down despite strong opposition from colleagues.","ua":"Він відмовився відступати, попри сильний опір колег."}},
  {"id":"w2639","en":"boil down to","ua":"зводитися до суті","pos":"phrasal","level":"B2","topic":"general","freqRank":2639,"example":{"en":"The whole argument boils down to a simple misunderstanding.","ua":"Вся суперечка зводиться до простого непорозуміння."}},
  {"id":"w2640","en":"build on","ua":"спиратися на (успіх або досвід)","pos":"phrasal","level":"B2","topic":"general","freqRank":2640,"example":{"en":"The new plan builds on the success of last year.","ua":"Новий план спирається на успіх минулого року."}},
  {"id":"w2641","en":"call off","ua":"скасовувати (захід або зустріч)","pos":"phrasal","level":"B2","topic":"general","freqRank":2641,"example":{"en":"They called off the outdoor event due to heavy rain.","ua":"Вони скасували вуличний захід через сильний дощ."}},
  {"id":"w2642","en":"come to terms with","ua":"змиритися з важкою ситуацією","pos":"phrasal","level":"B2","topic":"emotions","freqRank":2642,"example":{"en":"It took months to come to terms with the bad news.","ua":"Знадобилися місяці, щоб змиритися з поганими новинами."}},
  {"id":"w2643","en":"draw on","ua":"використовувати (досвід або ресурси)","pos":"phrasal","level":"B2","topic":"work","freqRank":2643,"example":{"en":"She drew on years of experience to solve the crisis.","ua":"Вона спиралася на роки досвіду, вирішуючи кризу."}},
  {"id":"w2644","en":"face up to","ua":"визнавати та стикатися з реальністю","pos":"phrasal","level":"B2","topic":"emotions","freqRank":2644,"example":{"en":"You need to face up to your responsibilities at work.","ua":"Тобі потрібно визнати та взяти на себе робочі обов'язки."}},
  {"id":"w2645","en":"factor in","ua":"враховувати при плануванні","pos":"phrasal","level":"B2","topic":"business","freqRank":2645,"example":{"en":"We must factor in the extra costs before signing the contract.","ua":"Ми повинні врахувати додаткові витрати перед підписанням контракту."}},
  {"id":"w2646","en":"fall through","ua":"зриватися (про план або угоду)","pos":"phrasal","level":"B2","topic":"general","freqRank":2646,"example":{"en":"Our plans to move abroad fell through at the last moment.","ua":"Наші плани переїхати за кордон зірвалися в останній момент."}},
  {"id":"w2647","en":"flesh out","ua":"деталізувати, розвивати ідею","pos":"phrasal","level":"B2","topic":"work","freqRank":2647,"example":{"en":"We need to flesh out this proposal before the meeting.","ua":"Нам потрібно деталізувати цю пропозицію до наради."}},
  {"id":"w2648","en":"follow through","ua":"доводити до кінця розпочату справу","pos":"phrasal","level":"B2","topic":"general","freqRank":2648,"example":{"en":"She always follows through on every promise she makes.","ua":"Вона завжди доводить до кінця кожну свою обіцянку."}},
  {"id":"w2649","en":"give way to","ua":"поступатися місцем; поступово замінюватися","pos":"phrasal","level":"B2","topic":"general","freqRank":2649,"example":{"en":"The old factory gave way to a modern shopping centre.","ua":"Стара фабрика поступилася місцем сучасному торговому центру."}},
  {"id":"w2650","en":"go along with","ua":"погоджуватися з пропозицією","pos":"phrasal","level":"B2","topic":"general","freqRank":2650,"example":{"en":"He went along with the decision to avoid any conflict.","ua":"Він погодився з рішенням, щоб уникнути конфлікту."}},
  {"id":"w2651","en":"head off","ua":"запобігати, попереджати проблему","pos":"phrasal","level":"B2","topic":"general","freqRank":2651,"example":{"en":"The manager headed off the problem before it became serious.","ua":"Менеджер запобіг проблемі до того, як вона стала серйозною."}},
  {"id":"w2652","en":"iron out","ua":"вирішувати (розбіжності або деталі)","pos":"phrasal","level":"B2","topic":"work","freqRank":2652,"example":{"en":"They met for an hour to iron out the remaining differences.","ua":"Вони зустрілися на годину, щоб вирішити розбіжності, що залишилися."}},
  {"id":"w2653","en":"live up to","ua":"відповідати (очікуванням або обіцянкам)","pos":"phrasal","level":"B2","topic":"general","freqRank":2653,"example":{"en":"The new product did not live up to our expectations.","ua":"Новий продукт не відповів нашим очікуванням."}},
  {"id":"w2654","en":"lock in","ua":"фіксувати (ціну або умову угоди)","pos":"phrasal","level":"B2","topic":"business","freqRank":2654,"example":{"en":"We locked in a low interest rate for five years.","ua":"Ми зафіксували низьку відсоткову ставку на п'ять років."}},
  {"id":"w2655","en":"map out","ua":"детально планувати (стратегію)","pos":"phrasal","level":"B2","topic":"work","freqRank":2655,"example":{"en":"The consultant helped us map out a clear growth strategy.","ua":"Консультант допоміг нам детально спланувати стратегію зростання."}},
  {"id":"w2656","en":"measure up","ua":"відповідати вимогам або стандартам","pos":"phrasal","level":"B2","topic":"work","freqRank":2656,"example":{"en":"His second album did not measure up to the first.","ua":"Його другий альбом не відповідав рівню першого."}},
  {"id":"w2657","en":"pan out","ua":"складатися, виявлятися (про результат)","pos":"phrasal","level":"B2","topic":"general","freqRank":2657,"example":{"en":"Let us wait to see how things pan out.","ua":"Давайте зачекаємо і побачимо, як усе складеться."}},
  {"id":"w2658","en":"phase out","ua":"поступово скасовувати або виводити з обігу","pos":"phrasal","level":"B2","topic":"business","freqRank":2658,"example":{"en":"The government plans to phase out coal power by 2030.","ua":"Уряд планує поступово відмовитися від вугільної енергетики до 2030 року."}},
  {"id":"w2659","en":"pick up on","ua":"помічати (деталь або натяк)","pos":"phrasal","level":"B2","topic":"general","freqRank":2659,"example":{"en":"She picked up on the error before anyone else did.","ua":"Вона помітила помилку раніше, ніж хто-небудь інший."}},
  {"id":"w2660","en":"pin down","ua":"точно визначати або зафіксовувати","pos":"phrasal","level":"B2","topic":"general","freqRank":2660,"example":{"en":"Can you pin down the exact cause of the error?","ua":"Чи можеш ти точно визначити причину помилки?"}},
  {"id":"w2661","en":"play down","ua":"применшувати (важливість або серйозність)","pos":"phrasal","level":"B2","topic":"communication","freqRank":2661,"example":{"en":"The spokesperson played down the severity of the situation.","ua":"Речник применшив серйозність ситуації."}},
  {"id":"w2662","en":"pull off","ua":"успішно виконувати складне завдання","pos":"phrasal","level":"B2","topic":"general","freqRank":2662,"example":{"en":"Against all odds, they managed to pull off the deal.","ua":"Всупереч усьому, їм вдалося укласти угоду."}},
  {"id":"w2663","en":"push through","ua":"домагатися прийняття рішення або закону","pos":"phrasal","level":"B2","topic":"general","freqRank":2663,"example":{"en":"The government pushed through the reforms despite public protests.","ua":"Уряд протягнув реформи, попри публічні протести."}},
  {"id":"w2664","en":"root out","ua":"викорінювати (проблему або корупцію)","pos":"phrasal","level":"B2","topic":"general","freqRank":2664,"example":{"en":"The new director vowed to root out corruption in the department.","ua":"Новий директор пообіцяв викорінити корупцію у відділі."}},
  {"id":"w2665","en":"rule out","ua":"виключати (варіант або можливість)","pos":"phrasal","level":"B2","topic":"general","freqRank":2665,"example":{"en":"The doctors ruled out cancer after the test results came back.","ua":"Лікарі виключили рак після отримання результатів аналізів."}},
  {"id":"w2666","en":"run out of","ua":"вичерпувати (запас чогось)","pos":"phrasal","level":"B2","topic":"general","freqRank":2666,"example":{"en":"We ran out of time before finishing the last question.","ua":"У нас закінчився час до завершення останнього питання."}},
  {"id":"w2667","en":"set aside","ua":"відкладати (гроші або час)","pos":"phrasal","level":"B2","topic":"money","freqRank":2667,"example":{"en":"Try to set aside some money each month for emergencies.","ua":"Намагайтеся відкладати трохи грошей щомісяця на непередбачені витрати."}},
  {"id":"w2668","en":"stand out","ua":"виділятися (серед інших)","pos":"phrasal","level":"B2","topic":"general","freqRank":2668,"example":{"en":"Her colourful portfolio made her stand out from other applicants.","ua":"Її яскраве портфоліо виділяло її серед інших кандидатів."}},
  {"id":"w2669","en":"stem from","ua":"походити від, бути результатом","pos":"phrasal","level":"B2","topic":"general","freqRank":2669,"example":{"en":"His anxiety stems from a difficult childhood experience.","ua":"Його тривожність походить з важкого дитячого досвіду."}},
  {"id":"w2670","en":"stir up","ua":"викликати (суперечку або почуття)","pos":"phrasal","level":"B2","topic":"emotions","freqRank":2670,"example":{"en":"The controversial article stirred up a lot of public debate.","ua":"Суперечлива стаття викликала широку публічну дискусію."}},
  {"id":"w2671","en":"stumble upon","ua":"випадково виявляти або знаходити","pos":"phrasal","level":"B2","topic":"general","freqRank":2671,"example":{"en":"She stumbled upon a rare book in the old bookshop.","ua":"Вона натрапила на рідкісну книгу у старій книгарні."}},
  {"id":"w2672","en":"sum up","ua":"підсумовувати (висновки або думки)","pos":"phrasal","level":"B2","topic":"communication","freqRank":2672,"example":{"en":"Let me sum up the key points of today's discussion.","ua":"Дозвольте мені підсумувати ключові моменти сьогоднішнього обговорення."}},
  {"id":"w2673","en":"tap into","ua":"використовувати (ресурс або потенціал)","pos":"phrasal","level":"B2","topic":"business","freqRank":2673,"example":{"en":"The firm hopes to tap into the growing Asian market.","ua":"Компанія сподівається скористатися азіатським ринком, що зростає."}},
  {"id":"w2674","en":"tear down","ua":"зносити (будівлю або структуру)","pos":"phrasal","level":"B2","topic":"general","freqRank":2674,"example":{"en":"They tore down the old factory to build new apartments.","ua":"Вони знесли стару фабрику, щоб побудувати нові квартири."}},
  {"id":"w2675","en":"tone down","ua":"пом'якшувати (тон або формулювання)","pos":"phrasal","level":"B2","topic":"communication","freqRank":2675,"example":{"en":"Please tone down the language in your official report.","ua":"Будь ласка, пом'якши формулювання в офіційному звіті."}},
  {"id":"w2676","en":"touch on","ua":"торкатися (теми) побіжно","pos":"phrasal","level":"B2","topic":"communication","freqRank":2676,"example":{"en":"The speaker briefly touched on the issue of inequality.","ua":"Доповідач побіжно торкнувся питання нерівності."}},
  {"id":"w2677","en":"turn around","ua":"докорінно змінювати ситуацію на краще","pos":"phrasal","level":"B2","topic":"business","freqRank":2677,"example":{"en":"The new CEO managed to turn around the failing company.","ua":"Новий генеральний директор зміг оздоровити компанію, що занепадала."}},
  {"id":"w2678","en":"ward off","ua":"відвертати (загрозу або хворобу)","pos":"phrasal","level":"B2","topic":"health","freqRank":2678,"example":{"en":"Regular exercise helps to ward off many common illnesses.","ua":"Регулярні фізичні вправи допомагають запобігти багатьом поширеним хворобам."}},
  {"id":"w2679","en":"weigh up","ua":"зважувати та порівнювати варіанти","pos":"phrasal","level":"B2","topic":"general","freqRank":2679,"example":{"en":"Take your time to weigh up all the options carefully.","ua":"Не поспішайте і уважно зважте всі варіанти."}},
  {"id":"w2680","en":"wind up","ua":"опинятися (внаслідок низки подій)","pos":"phrasal","level":"B2","topic":"general","freqRank":2680,"example":{"en":"He wound up paying far more than he had planned.","ua":"Він врешті-решт заплатив набагато більше, ніж планував."}},
  {"id":"w2681","en":"write off","ua":"списувати борг; вважати безнадійним","pos":"phrasal","level":"B2","topic":"business","freqRank":2681,"example":{"en":"The bank agreed to write off part of the outstanding debt.","ua":"Банк погодився списати частину непогашеної заборгованості."}},
  {"id":"w2682","en":"back out","ua":"відмовлятися від угоди в останній момент","pos":"phrasal","level":"B2","topic":"general","freqRank":2682,"example":{"en":"One supplier backed out of the contract at the last minute.","ua":"Один постачальник відмовився від контракту в останню хвилину."}},
  {"id":"w2683","en":"branch out","ua":"розширювати діяльність у нову сферу","pos":"phrasal","level":"B2","topic":"business","freqRank":2683,"example":{"en":"The bookshop decided to branch out into selling stationery.","ua":"Книгарня вирішила розширити діяльність на продаж канцтоварів."}},
  {"id":"w2684","en":"burn out","ua":"вигоряти від перевтоми","pos":"phrasal","level":"B2","topic":"health","freqRank":2684,"example":{"en":"She burned out after working seventy hours a week for months.","ua":"Вона вигоріла після кількох місяців роботи по сімдесят годин на тиждень."}},
  {"id":"w2685","en":"cash in on","ua":"скористатися з вигідної ситуації","pos":"phrasal","level":"B2","topic":"money","freqRank":2685,"example":{"en":"Some companies cashed in on the sudden rise in demand.","ua":"Деякі компанії скористалися з раптового зростання попиту."}},
  {"id":"w2686","en":"single out","ua":"виділяти когось зі спільної групи","pos":"phrasal","level":"B2","topic":"general","freqRank":2686,"example":{"en":"The coach singled out three players for special training sessions.","ua":"Тренер виділив трьох гравців для спеціальних тренувань."}}
]
